MANIFEST.in
README.rst
setup.py
placeholder/__init__.py
placeholder/bootstrap.py
placeholder/helpers.py
placeholder/partials.py
placeholder/controllers/__init__.py
placeholder/controllers/root.py
placeholder/lib/__init__.py
placeholder/public/Marlboro.ttf
placeholder/public/__init__.py
placeholder/public/css/style.css
placeholder/templates/__init__.py
placeholder/templates/index.html
placeholder/templates/little_partial.html
tgapp_placeholder.egg-info/PKG-INFO
tgapp_placeholder.egg-info/SOURCES.txt
tgapp_placeholder.egg-info/dependency_links.txt
tgapp_placeholder.egg-info/entry_points.txt
tgapp_placeholder.egg-info/not-zip-safe
tgapp_placeholder.egg-info/requires.txt
tgapp_placeholder.egg-info/top_level.txt