Metadata-Version: 1.0
Name: tgapp-placeholder
Version: 1.0.1
Summary: Placeholder image on the fly for Turbogears2
Home-page: http://github.com/puria/tgapp-placeholder
Author: Puria Nafisi Azizi
Author-email: puria.nafisi@axant.it
License: WTFPL
Keywords: turbogears2.application placeholder dummy image
Platform: UNKNOWN
